main/__init__.py
ppputils-0.1.dist-info/LICENSE
ppputils-0.1.dist-info/METADATA
ppputils-0.1.dist-info/WHEEL
ppputils-0.1.dist-info/top_level.txt
ppputils-0.1.dist-info/RECORD
