Metadata-Version: 2.1
Name: ppputils
Version: 0.1
Summary: init code
Home-page: https://github.com/puffhub/ppputils
Author: Peter Puff
Author-email: 
License: MIT
License-File: LICENSE
